idlescape/__init__.py
idlescape/character.py
idlescape/cli.py
idlescape/experience_to_level.py
idlescape/game.py
idlescape/game_data.py
idlescape/data/activities.json
idlescape/data/activity_option_experience_rewards.json
idlescape/data/activity_option_item_costs.json
idlescape/data/activity_option_item_rewards.json
idlescape/data/activity_option_skill_requirements.json
idlescape/data/activity_options.json
idlescape/data/experience_to_level.json
idlescape/data/items.json
idlescape-0.3.0.dist-info/METADATA
idlescape-0.3.0.dist-info/WHEEL
idlescape-0.3.0.dist-info/entry_points.txt
idlescape-0.3.0.dist-info/top_level.txt
idlescape-0.3.0.dist-info/RECORD
