Metadata-Version: 2.4
Name: idlescape
Version: 0.3.0
Summary: An idle game. Collect resources, level up skills.
Author: Ben Walzer
License-Expression: Apache-2.0
Project-URL: Homepage, https://github.com/BWalzer/idlescape
Requires-Python: >=3.13
Requires-Dist: click>=8.2.1
Requires-Dist: pendulum>=3.0.0
Requires-Dist: questionary>=2.1.0
Requires-Dist: sqlalchemy>=2.0.41
